{"name":"battle_101","images":[{"py":23,"a":2.25,"name":"rock-4","b":0,"tx":58.1,"c":0,"ty":1521.05,"px":64.5,"d":2.25},{"a":1,"name":"road-h","b":0,"tx":298.2,"c":0,"ty":1379.85,"d":1},{"a":1,"name":"road-v","b":0,"tx":721.75,"c":0,"ty":1008.5,"d":1},{"py":0,"a":1.18948364257813,"name":"background-0-l","b":0,"tx":0,"c":0,"ty":3.1,"px":0.05,"d":1.18948364257813},{"py":0,"a":1.1715087890625,"name":"background-0-r","b":0,"tx":701.7,"c":0,"ty":0,"px":2.95,"d":1.1715087890625},{"py":0,"a":1.9007568359375,"name":"foreground-0-l","b":0,"tx":0,"c":0,"ty":1549.1,"px":0,"d":1.9007568359375},{"py":0,"a":1.14199829101563,"name":"foreground-0-r","b":0,"tx":573.05,"c":0,"ty":1656.6,"px":0,"d":1.14199829101563},{"py":19,"a":2.25,"name":"bush-7","b":0,"tx":-14.75,"c":0,"ty":744.8,"px":41.5,"d":2.25},{"py":28,"a":2.25003051757813,"name":"bush-4","b":0,"tx":8.1,"c":0,"ty":560.85,"px":35.55,"d":2.25003051757813},{"py":28.5,"a":2.25003051757813,"name":"hole-1","b":0,"tx":877.25,"c":0,"ty":1185.75,"px":35.5,"d":2.25003051757813},{"py":34,"a":1.80490112304688,"name":"hole-2","b":0,"tx":407.5,"c":0,"ty":658.9,"px":51,"d":1.80490112304688},{"py":15,"a":2.24998474121094,"name":"rock-3","b":0,"tx":472.1,"c":0,"ty":400.1,"px":27,"d":2.24998474121094},{"py":18,"a":2.25,"name":"bush-0","b":0,"tx":472.1,"c":0,"ty":124.45,"px":30,"d":2.25},{"py":28,"a":2.25003051757813,"name":"bush-4","b":0,"tx":355.7,"c":0,"ty":225.95,"px":35.55,"d":2.25003051757813},{"py":71.5,"a":1.29998779296875,"name":"tree-0","b":0,"tx":496.65,"c":0,"ty":1048.25,"px":61,"d":1.29998779296875},{"a":1,"name":"building-plot","b":0,"tx":646,"c":0,"ty":1361.4,"d":1},{"py":19,"a":2.25,"name":"bush-7","b":0,"tx":655.25,"c":0,"ty":1588.6,"px":41.5,"d":2.25},{"py":25,"a":2.25,"name":"chair-1","b":0,"tx":834.5,"c":0,"ty":632.3,"px":45,"d":2.25},{"py":15,"a":2.24998474121094,"name":"rock-3","b":0,"tx":637.9,"c":0,"ty":974.75,"px":27,"d":2.24998474121094},{"a":1,"name":"road-v","b":0,"tx":264.3,"c":0,"ty":544.75,"d":1},{"a":1,"name":"road-v","b":0,"tx":264.3,"c":0,"ty":675.25,"d":1},{"a":1,"name":"road-v","b":0,"tx":719.35,"c":0,"ty":513.45,"d":1},{"a":1,"name":"road-v","b":0,"tx":262.7,"c":0,"ty":1006.65,"d":1},{"a":1,"name":"building-plot","b":0,"tx":190,"c":0,"ty":977.65,"d":1},{"a":1,"name":"road-v","b":0,"tx":719.35,"c":0,"ty":876.15,"d":1},{"a":1,"name":"building-plot","b":0,"tx":655.25,"c":0,"ty":803.45,"d":1},{"py":201.5,"a":0.937835693359375,"name":"road-v","b":0.347030639648438,"tx":489.6,"c":-0.44207763671875,"ty":929.45,"px":44.45,"d":1.19476318359375},{"py":201.45,"a":0.945831298828125,"name":"road-v","b":0.324615478515625,"tx":685.9,"c":-0.422821044921875,"ty":461.6,"px":44.5,"d":1.23199462890625},{"a":1,"name":"road-h","b":0,"tx":353.3,"c":0,"ty":465.75,"d":1},{"py":63,"a":0.437835693359375,"name":"building-plot","b":0,"tx":669.2,"c":0,"ty":505.25,"px":111,"d":0.627029418945313},{"py":63,"a":0.386764526367188,"name":"building-plot","b":0,"tx":273.15,"c":0,"ty":1215.05,"px":111.05,"d":1.58648681640625},{"a":1,"name":"building-plot","b":0,"tx":429,"c":0,"ty":897,"d":1},{"a":1,"name":"building-plot","b":0,"tx":669.2,"c":0,"ty":434.85,"d":1},{"py":71.5,"a":1.29998779296875,"name":"tree-0","b":0,"tx":539.55,"c":0,"ty":1103.65,"px":61,"d":1.29998779296875},{"py":71.5,"a":1.29998779296875,"name":"tree-0","b":0,"tx":460.25,"c":0,"ty":1196.6,"px":61,"d":1.29998779296875},{"py":71.5,"a":1.29998779296875,"name":"tree-0","b":0,"tx":551.75,"c":0,"ty":1456.15,"px":61,"d":1.29998779296875},{"a":1,"name":"building-plot","b":0,"tx":196.2,"c":0,"ty":1346.65,"d":1},{"a":1,"name":"building-plot","b":0,"tx":199.95,"c":0,"ty":447.05,"d":1}],"hasIntro":false,"places":[{"troopType":-1,"type":1,"links":[5,6,3],"index":0,"tutorIndex":-3,"enabled":true},{"troopType":-1,"type":1,"links":[6,4,2],"index":1,"tutorIndex":-3,"enabled":true},{"troopType":-1,"type":1,"links":[1,5],"index":2,"tutorIndex":-3,"enabled":true},{"troopType":-1,"type":1,"links":[0,4],"index":3,"tutorIndex":-3,"enabled":true},{"troopType":1,"type":11,"links":[1,3],"index":4,"tutorIndex":-3,"enabled":true},{"troopType":0,"type":11,"links":[0,2],"index":5,"tutorIndex":-3,"enabled":true},{"troopType":-1,"type":1,"links":[0,1],"index":6,"tutorIndex":-3,"enabled":true}],"times":[100,100,100],"hasFinal":false}