{"places":[{"links":[1,7],"type":41,"tutorIndex":-3,"index":0,"enabled":true,"troopType":1},{"links":[0,2,9],"type":1,"tutorIndex":-3,"index":1,"enabled":true,"troopType":1},{"links":[1,6],"type":41,"tutorIndex":-3,"index":2,"enabled":true,"troopType":1},{"links":[4,6],"type":41,"tutorIndex":-3,"index":3,"enabled":true,"troopType":0},{"links":[3,5,8],"type":1,"tutorIndex":-3,"index":4,"enabled":true,"troopType":0},{"links":[4,7],"type":41,"tutorIndex":-3,"index":5,"enabled":true,"troopType":0},{"links":[2,3],"type":11,"tutorIndex":-3,"index":6,"enabled":true,"troopType":-1},{"links":[0,5],"type":11,"tutorIndex":-3,"index":7,"enabled":true,"troopType":-1},{"links":[4,9],"type":1,"tutorIndex":-3,"index":8,"enabled":true,"troopType":-1},{"links":[1,8],"type":1,"tutorIndex":-3,"index":9,"enabled":true,"troopType":-1}],"hasIntro":false,"images":[{"py":201.45,"px":44.45,"a":0.999969482421875,"name":"road-v","b":0.0000152587890625,"tx":497.15,"c":-0.00006103515625,"ty":504.85,"d":2.26823425292969},{"py":201.45,"px":44.5,"a":0.5,"name":"road-v","b":-0.866012573242188,"tx":526.3,"c":0.497787475585938,"ty":544.45,"d":0.287399291992188},{"py":201.45,"px":44.5,"a":0.5,"name":"road-v","b":-0.866012573242188,"tx":307.4,"c":0.497787475585938,"ty":1336.55,"d":0.287399291992188},{"py":201.45,"px":44.55,"a":0.499984741210938,"name":"road-v","b":0.866012573242188,"tx":510.15,"c":-0.524063110351563,"ty":464.25,"d":0.30255126953125},{"py":201.45,"px":44.55,"a":0.499984741210938,"name":"road-v","b":0.866012573242188,"tx":735.25,"c":-0.524063110351563,"ty":1256.35,"d":0.30255126953125},{"a":1,"name":"road-v","b":0,"tx":703.95,"c":0,"ty":930.25,"d":1},{"a":1,"name":"road-v","b":0,"tx":703.95,"c":0,"ty":633.5,"d":1},{"a":1,"name":"road-v","b":0,"tx":294.35,"c":0,"ty":585.35,"d":1},{"a":1,"name":"road-v","b":0,"tx":294.35,"c":0,"ty":913.05,"d":1},{"py":19,"px":41.5,"a":2.25,"name":"bush-7","b":0,"tx":481.05,"c":0,"ty":191.95,"d":2.25},{"a":1,"name":"bush-4","b":0,"tx":780.95,"c":0,"ty":1660.25,"d":1},{"a":1,"name":"bush-5","b":0,"tx":726.6,"c":0,"ty":1700.25,"d":1},{"a":1,"name":"bush-3","b":0,"tx":636.1,"c":0,"ty":1677.55,"d":1},{"a":1,"name":"building-plot","b":0,"tx":627.65,"c":0,"ty":1260.1,"d":1},{"a":1,"name":"building-plot","b":0,"tx":429.95,"c":0,"ty":1355.9,"d":1},{"a":1,"name":"building-plot","b":0,"tx":212,"c":0,"ty":1260.1,"d":1},{"a":1,"name":"building-plot","b":0,"tx":627.8,"c":0,"ty":898.4,"d":1},{"a":1,"name":"building-plot","b":0,"tx":222.85,"c":0,"ty":898.4,"d":1},{"a":1,"name":"building-plot","b":0,"tx":624.7,"c":0,"ty":536.7,"d":1},{"a":1,"name":"building-plot","b":0,"tx":426.85,"c":0,"ty":437.8,"d":1},{"a":1,"name":"building-plot","b":0,"tx":225.95,"c":0,"ty":539.8,"d":1},{"a":1,"name":"building-plot","b":0,"tx":423.9,"c":0,"ty":1074.1,"d":1},{"a":1,"name":"building-plot","b":0,"tx":433.1,"c":0,"ty":701.2,"d":1},{"a":1,"name":"tree-0","b":0,"tx":875.2,"c":0,"ty":491.8,"d":1},{"a":1,"name":"tree-0","b":0,"tx":8.5,"c":0,"ty":487.8,"d":1},{"a":1,"name":"tree-0","b":0,"tx":105.85,"c":0,"ty":1092.05,"d":1},{"a":1,"name":"tree-0","b":0,"tx":51.6,"c":0,"ty":980.05,"d":1},{"a":1,"name":"tree-0","b":0,"tx":899.2,"c":0,"ty":634.05,"d":1},{"a":1,"name":"tree-0","b":0,"tx":439.95,"c":0,"ty":259.55,"d":1},{"a":1,"name":"tree-0","b":0,"tx":776.5,"c":0,"ty":1021.4,"d":1},{"a":1,"name":"tree-0","b":0,"tx":51.6,"c":0,"ty":1221.25,"d":1},{"a":1,"name":"tree-0","b":0,"tx":185.35,"c":0,"ty":654.35,"d":1},{"a":1,"name":"tree-0","b":0,"tx":899,"c":0,"ty":876.35,"d":1},{"a":1,"name":"tree-0","b":0,"tx":64.05,"c":0,"ty":891.3,"d":1},{"a":1,"name":"tree-0","b":0,"tx":88.8,"c":0,"ty":1436.05,"d":1},{"a":1,"name":"tree-0","b":0,"tx":171.75,"c":0,"ty":1548.25,"d":1},{"a":1,"name":"tree-0","b":0,"tx":62.75,"c":0,"ty":351.85,"d":1},{"a":1,"name":"tree-0","b":0,"tx":117.5,"c":0,"ty":435.65,"d":1},{"py":14.45,"px":19.5,"a":1.907470703125,"name":"chair-0","b":0,"tx":899,"c":0,"ty":371.55,"d":1.907470703125},{"a":1,"name":"tree-0","b":0,"tx":961.3,"c":0,"ty":1014.05,"d":1},{"a":1,"name":"bush-5","b":0,"tx":926.3,"c":0,"ty":1156.1,"d":1},{"a":1,"name":"bush-3","b":0,"tx":835.8,"c":0,"ty":1133.4,"d":1},{"a":1,"name":"tree-0","b":0,"tx":926.3,"c":0,"ty":1204.05,"d":1},{"a":1,"name":"tree-0","b":0,"tx":887.4,"c":0,"ty":1348,"d":1},{"a":1,"name":"tree-0","b":0,"tx":683.95,"c":0,"ty":303.95,"d":1},{"a":1,"name":"tree-0","b":0,"tx":503,"c":0,"ty":1548.25,"d":1},{"a":1,"name":"tree-0","b":0,"tx":749.8,"c":0,"ty":1527.7,"d":1},{"a":1,"name":"tree-0","b":0,"tx":361.45,"c":0,"ty":1566.3,"d":1},{"a":1,"name":"tree-0","b":0,"tx":640.8,"c":0,"ty":1500.65,"d":1},{"py":44.4,"px":66.05,"a":1.06471252441406,"name":"tree-0","b":0.078399658203125,"tx":911.3,"c":-0.0765838623046875,"ty":558.8,"d":1.04006958007813}],"hasFinal":false,"times":[75,100,125,100],"name":"battle_202"}