{"images":[{"px":44.5,"py":201.5,"a":0.74615478515625,"name":"road-v","b":-0.665740966796875,"tx":216,"c":1.12432861328125,"ty":692.55,"d":1.2601318359375},{"px":0.05,"py":0,"a":1.18948364257813,"name":"background-0-l","b":0,"tx":0,"c":0,"ty":0,"d":1.18948364257813},{"px":2.95,"py":0,"a":1.1715087890625,"name":"background-0-r","b":0,"tx":704.75,"c":0,"ty":-3.6,"d":1.1715087890625},{"px":0,"py":0,"a":1.9007568359375,"name":"foreground-0-l","b":0,"tx":-8.9,"c":0,"ty":1541.25,"d":1.9007568359375},{"px":0,"py":0,"a":1.14199829101563,"name":"foreground-0-r","b":0,"tx":572.95,"c":0,"ty":1649.1,"d":1.14199829101563},{"px":30.05,"py":17.95,"a":1.41864013671875,"name":"bush-0","b":0,"tx":931.05,"c":0,"ty":1403.75,"d":1.41864013671875},{"px":35.55,"py":28,"a":1.59835815429688,"name":"bush-4","b":0,"tx":874.1,"c":0,"ty":551.1,"d":1.59835815429688},{"px":45.05,"py":25.05,"a":2.25003051757813,"name":"chair-1","b":0,"tx":715.6,"c":0,"ty":319.5,"d":2.25003051757813},{"px":39.5,"py":17.5,"a":2.25,"name":"rock-0","b":0,"tx":622.5,"c":0,"ty":725.05,"d":2.25},{"px":27,"py":15,"a":1.71110534667969,"name":"rock-3","b":0,"tx":848.1,"c":0,"ty":938.5,"d":1.71110534667969},{"a":0.861160278320313,"name":"road-h","b":0.50830078125,"tx":351.5,"c":-0.50830078125,"ty":301.55,"d":0.861160278320313},{"a":1,"name":"road-h","b":0,"tx":324.2,"c":0,"ty":1186.85,"d":1},{"a":0.87652587890625,"name":"road-v","b":0.481353759765625,"tx":713.55,"c":-0.481353759765625,"ty":1121.2,"d":0.87652587890625},{"px":35.55,"py":27.95,"a":1.52655029296875,"name":"bush-4","b":0,"tx":12.3,"c":0,"ty":915.45,"d":1.52655029296875},{"px":19.5,"py":14.5,"a":2.25,"name":"chair-0","b":0,"tx":858.3,"c":0,"ty":276.6,"d":2.25},{"px":41.45,"py":19,"a":1.52653503417969,"name":"bush-7","b":0,"tx":-8.65,"c":0,"ty":1088.2,"d":1.52653503417969},{"a":0.595306396484375,"name":"road-v","b":-0.803482055664063,"tx":214.7,"c":0.803482055664063,"ty":1235.2,"d":0.595306396484375},{"a":1,"name":"building-plot","b":0,"tx":166.35,"c":0,"ty":1175.75,"d":1},{"a":1,"name":"building-plot","b":0,"tx":452.85,"c":0,"ty":1380,"d":1},{"px":30,"py":18,"a":1.82330322265625,"name":"bush-0","b":0,"tx":644.2,"c":0,"ty":247.6,"d":1.82330322265625},{"a":1,"name":"tree-0","b":0,"tx":423.6,"c":0,"ty":0,"d":1},{"a":1,"name":"tree-0","b":0,"tx":560.95,"c":0,"ty":-38.15,"d":1},{"a":1,"name":"tree-0","b":0,"tx":423.6,"c":0,"ty":-71.5,"d":1},{"a":1,"name":"tree-0","b":0,"tx":459.8,"c":0,"ty":116.6,"d":1},{"a":1,"name":"tree-0","b":0,"tx":499.95,"c":0,"ty":33.35,"d":1},{"a":1,"name":"tree-0","b":0,"tx":559.95,"c":0,"ty":88.65,"d":1},{"a":1,"name":"tree-0","b":0,"tx":484.6,"c":0,"ty":-71.5,"d":1},{"a":1,"name":"tree-0","b":0,"tx":158.25,"c":0,"ty":172.15,"d":1},{"a":1,"name":"tree-0","b":0,"tx":91.6,"c":0,"ty":206.2,"d":1},{"a":1.59835815429688,"name":"bush-4","b":0,"tx":837.2,"c":0,"ty":749.8,"d":1.59835815429688},{"a":1.59835815429688,"name":"bush-4","b":0,"tx":735.5,"c":0,"ty":810.75,"d":1.59835815429688},{"px":35.5,"py":28,"a":1.41867065429688,"name":"bush-4","b":0,"tx":816.55,"c":0,"ty":1409.2,"d":1.41867065429688},{"a":0.971237182617188,"name":"road-v","b":0.23809814453125,"tx":275.15,"c":-0.23809814453125,"ty":316.3,"d":0.971237182617188},{"a":1,"name":"building-plot","b":0,"tx":223.05,"c":0,"ty":279.5,"d":1},{"px":28.5,"py":16.5,"a":1.59832763671875,"name":"bush-3","b":0,"tx":826.7,"c":0,"ty":799.15,"d":1.59832763671875},{"a":1,"name":"tree-0","b":0,"tx":44.35,"c":0,"ty":757.25,"d":1},{"px":28.5,"py":16.5,"a":2.25,"name":"bush-3","b":0,"tx":901.3,"c":0,"ty":1214.6,"d":2.25},{"a":1,"name":"tree-0","b":0,"tx":213.6,"c":0,"ty":1032.1,"d":1},{"a":0.934158325195313,"name":"road-h","b":-0.3568115234375,"tx":267.9,"c":0.3568115234375,"ty":627.25,"d":0.934158325195313},{"a":1,"name":"building-plot","b":0,"tx":554.8,"c":0,"ty":455.2,"d":1},{"px":41.5,"py":19,"a":1.82330322265625,"name":"bush-7","b":0,"tx":484.6,"c":0,"ty":292.8,"d":1.82330322265625},{"a":1,"name":"building-plot","b":0,"tx":113.9,"c":0,"ty":598.85,"d":1},{"px":39.5,"py":17.5,"a":2.25,"name":"rock-0","b":0,"tx":851.8,"c":0,"ty":644.4,"d":2.25},{"a":1,"name":"tree-0","b":0,"tx":790.8,"c":0,"ty":572.9,"d":1},{"a":1,"name":"tree-0","b":0,"tx":790.8,"c":0,"ty":964.15,"d":1},{"a":1,"name":"tree-0","b":0,"tx":772.3,"c":0,"ty":964.15,"d":1},{"a":1,"name":"tree-0","b":0,"tx":881.8,"c":0,"ty":1006.45,"d":1},{"px":19.5,"py":14.5,"a":2.25,"name":"chair-0","b":0,"tx":3.85,"c":0,"ty":1349.65,"d":2.25},{"px":27,"py":15,"a":1.71110534667969,"name":"rock-3","b":0,"tx":45.4,"c":0,"ty":453.95,"d":1.71110534667969},{"a":1,"name":"tree-0","b":0,"tx":-30.4,"c":0,"ty":479.6,"d":1},{"a":1,"name":"tree-0","b":0,"tx":-30.4,"c":0,"ty":551.1,"d":1},{"a":1,"name":"tree-0","b":0,"tx":193.4,"c":0,"ty":821.15,"d":1},{"a":1,"name":"tree-0","b":0,"tx":631.6,"c":0,"ty":97.05,"d":1},{"a":1,"name":"tree-0","b":0,"tx":595.35,"c":0,"ty":-1.15,"d":1},{"a":1,"name":"tree-0","b":0,"tx":401,"c":0,"ty":17,"d":1},{"a":1,"name":"tree-0","b":0,"tx":71.4,"c":0,"ty":396.45,"d":1},{"px":39.55,"py":17.5,"a":1.78459167480469,"name":"rock-0","b":0,"tx":481.55,"c":0,"ty":1282.9,"d":1.78459167480469},{"a":1,"name":"building-plot","b":0,"tx":388.35,"c":0,"ty":863.85,"d":1},{"a":1,"name":"building-plot","b":0,"tx":622.45,"c":0,"ty":1131.15,"d":1},{"a":1,"name":"tree-0","b":0,"tx":301.6,"c":0,"ty":71.5,"d":1},{"a":1,"name":"tree-0","b":0,"tx":240.6,"c":0,"ty":143,"d":1},{"px":39.5,"py":17.5,"a":2.25,"name":"rock-0","b":0,"tx":776.8,"c":0,"ty":1679.1,"d":2.25}],"hasIntro":false,"hasFinal":false,"times":[30,55,70],"places":[{"tutorIndex":-3,"links":[1,4,6],"type":1,"index":0,"enabled":true,"troopType":-1},{"tutorIndex":-3,"links":[0,4],"type":1,"index":1,"enabled":true,"troopType":0},{"tutorIndex":-3,"links":[3,5],"type":13,"index":2,"enabled":true,"troopType":1},{"tutorIndex":-3,"links":[2,5],"type":1,"index":3,"enabled":true,"troopType":-1},{"tutorIndex":-3,"links":[0,1],"type":1,"index":4,"enabled":true,"troopType":-1},{"tutorIndex":-3,"links":[2,3,6],"type":1,"index":5,"enabled":true,"troopType":-1},{"tutorIndex":-3,"links":[0,5],"type":43,"index":6,"enabled":true,"troopType":-1}],"name":"quest_19"}