<DOMSymbolItem xmlns:xsi="http://www.w3.org/2001/XMLSchema-instance" xmlns="http://ns.adobe.com/xfl/2008/" name="place_mc" itemID="5936f750-00000ae9" linkageExportForAS="true" linkageClassName="com.gt.towers.editor.PlaceComponent" lastModified="1499162273" lastUniqueIdentifier="11">
  <timeline>
    <DOMTimeline name="place_mc">
      <layers>
        <DOMLayer name="tutor_btn" color="#9933CC" current="true" isSelected="true" autoNamed="false">
          <frames>
            <DOMFrame index="0" keyMode="9728">
              <elements>
                <DOMSymbolInstance libraryItemName="num_input" name="tutor_input" selected="true" centerPoint3DX="-91.5" centerPoint3DY="38.9">
                  <matrix>
                    <Matrix tx="-105.85" ty="24.65"/>
                  </matrix>
                  <transformationPoint>
                    <Point/>
                  </transformationPoint>
                </DOMSymbolInstance>
                <DOMSymbolInstance libraryItemName="num_btn" name="enabled_btn" centerPoint3DX="-91.5" centerPoint3DY="-4.55">
                  <matrix>
                    <Matrix tx="-105.85" ty="-18.8"/>
                  </matrix>
                  <transformationPoint>
                    <Point/>
                  </transformationPoint>
                </DOMSymbolInstance>
              </elements>
            </DOMFrame>
          </frames>
        </DOMLayer>
        <DOMLayer name="type_btn" color="#FF800A" autoNamed="false">
          <frames>
            <DOMFrame index="0" keyMode="9728">
              <elements>
                <DOMSymbolInstance libraryItemName="num_btn" name="type_btn" centerPoint3DX="115.2" centerPoint3DY="-4.55">
                  <matrix>
                    <Matrix tx="100.85" ty="-18.8"/>
                  </matrix>
                  <transformationPoint>
                    <Point/>
                  </transformationPoint>
                </DOMSymbolInstance>
              </elements>
            </DOMFrame>
          </frames>
        </DOMLayer>
        <DOMLayer name="level_btn" color="#4FFFFF" autoNamed="false">
          <frames>
            <DOMFrame index="0" keyMode="9728">
              <elements>
                <DOMSymbolInstance libraryItemName="num_btn" name="level_btn" centerPoint3DX="115.2" centerPoint3DY="38.9">
                  <matrix>
                    <Matrix tx="100.85" ty="24.65"/>
                  </matrix>
                  <transformationPoint>
                    <Point/>
                  </transformationPoint>
                </DOMSymbolInstance>
              </elements>
            </DOMFrame>
          </frames>
        </DOMLayer>
        <DOMLayer name="index_txt" color="#9933CC" autoNamed="false">
          <frames>
            <DOMFrame index="0" keyMode="9728">
              <elements>
                <DOMDynamicText name="index_txt" fontRenderingMode="device" width="66.05" height="45.1" isSelectable="false" lineType="multiline">
                  <matrix>
                    <Matrix tx="-21.5" ty="33.55"/>
                  </matrix>
                  <textRuns>
                    <DOMTextRun>
                      <characters>0</characters>
                      <textAttrs>
                        <DOMTextAttrs alignment="center" aliasText="false" size="32" bitmapSize="640" face="Arial-Black"/>
                      </textAttrs>
                    </DOMTextRun>
                  </textRuns>
                </DOMDynamicText>
              </elements>
            </DOMFrame>
          </frames>
        </DOMLayer>
        <DOMLayer name="body" color="#4FFF4F" autoNamed="false">
          <frames>
            <DOMFrame index="0" keyMode="9728">
              <elements>
                <DOMSymbolInstance libraryItemName="building-body" name="body_mc" centerPoint3DY="-66.15">
                  <matrix>
                    <Matrix ty="-66.15"/>
                  </matrix>
                  <transformationPoint>
                    <Point/>
                  </transformationPoint>
                </DOMSymbolInstance>
                <DOMSymbolInstance libraryItemName="radius_mc" name="radius_mc" centerPoint3DX="100" centerPoint3DY="70">
                  <transformationPoint>
                    <Point x="100" y="70"/>
                  </transformationPoint>
                </DOMSymbolInstance>
              </elements>
            </DOMFrame>
          </frames>
        </DOMLayer>
      </layers>
    </DOMTimeline>
  </timeline>
</DOMSymbolItem>