{"name":"quest_39","times":[170,190,210,40],"places":[{"links":[1,6,7],"type":43,"index":0,"tutorIndex":-3,"enabled":true,"troopType":-1},{"links":[0],"type":13,"index":1,"tutorIndex":-3,"enabled":true,"troopType":1},{"links":[9,3],"type":1,"index":2,"tutorIndex":-3,"enabled":true,"troopType":-1},{"links":[2,10,4],"type":43,"index":3,"tutorIndex":-3,"enabled":true,"troopType":-1},{"links":[3],"type":13,"index":4,"tutorIndex":-3,"enabled":true,"troopType":0},{"links":[8,9],"type":43,"index":5,"tutorIndex":-3,"enabled":true,"troopType":-1},{"links":[0],"type":11,"index":6,"tutorIndex":-3,"enabled":true,"troopType":1},{"links":[0,8],"type":1,"index":7,"tutorIndex":-3,"enabled":true,"troopType":-1},{"links":[5,7],"type":1,"index":8,"tutorIndex":-3,"enabled":true,"troopType":-1},{"links":[2,5],"type":1,"index":9,"tutorIndex":-3,"enabled":true,"troopType":-1},{"links":[3],"type":11,"index":10,"tutorIndex":-3,"enabled":true,"troopType":0}],"hasIntro":false,"images":[{"py":392.65,"a":-0.748443603515625,"name":"road-v","b":0.912734985351563,"tx":800,"c":-0.424392700195313,"ty":1317.95,"px":46.75,"d":-0.347991943359375},{"py":392.55,"a":-0.719192504882813,"name":"road-v","b":-0.93597412109375,"tx":381.7,"c":0.435195922851563,"ty":1390.9,"px":46.8,"d":-0.334381103515625},{"py":392.4,"a":-0.557525634765625,"name":"road-v","b":1.0404052734375,"tx":573.35,"c":-0.795303344726563,"ty":1154.85,"px":46.75,"d":-0.426177978515625},{"py":392.65,"a":-1.18008422851563,"name":"road-v","b":-0.025909423828125,"tx":293.7,"c":0.0120391845703125,"ty":1071,"px":46.75,"d":-0.548690795898438},{"py":392.55,"a":-0.016448974609375,"name":"road-v","b":-1.18026733398438,"tx":277.15,"c":0.548782348632813,"ty":925.1,"px":46.75,"d":-0.0076446533203125},{"py":392.55,"a":-0.016448974609375,"name":"road-v","b":-1.18026733398438,"tx":555.25,"c":0.548782348632813,"ty":923,"px":46.75,"d":-0.0076446533203125},{"py":392.6,"a":-1.18002319335938,"name":"road-v","b":-0.02862548828125,"tx":882.05,"c":0.0133209228515625,"ty":880.95,"px":46.85,"d":-0.548660278320313},{"py":392.6,"a":-0.701416015625,"name":"road-v","b":0.949356079101563,"tx":835.2,"c":-0.434661865234375,"ty":623.3,"px":46.9,"d":-0.321136474609375},{"py":392.6,"a":-0.788330078125,"name":"road-v","b":-0.87847900390625,"tx":642.9,"c":0.4783935546875,"ty":579.25,"px":46.7,"d":-0.429290771484375},{"py":392.5,"a":-0.636642456054688,"name":"road-v","b":0.993972778320313,"tx":606.75,"c":-0.582015991210938,"ty":490.8,"px":46.8,"d":-0.372772216796875},{"py":0,"a":1.18948364257813,"name":"background-0-l","b":0,"tx":0,"c":0,"ty":3.1,"px":0.05,"d":1.18948364257813},{"py":0,"a":1.1715087890625,"name":"background-0-r","b":0,"tx":701.7,"c":0,"ty":0,"px":2.95,"d":1.1715087890625},{"py":0,"a":1.9007568359375,"name":"foreground-0-l","b":0,"tx":-1.3,"c":0,"ty":1547.45,"px":0,"d":1.9007568359375},{"py":0,"a":1.14199829101563,"name":"foreground-0-r","b":0,"tx":573.05,"c":0,"ty":1656.6,"px":0,"d":1.14199829101563},{"py":18,"a":2.25,"name":"bush-0","b":0,"tx":-45.1,"c":0,"ty":1203.35,"px":30,"d":2.25},{"py":19,"a":2.25,"name":"bush-7","b":0,"tx":572.75,"c":0,"ty":1026.9,"px":41.5,"d":2.25},{"py":28,"a":2.25003051757813,"name":"bush-4","b":0,"tx":81.9,"c":0,"ty":1189.45,"px":35.55,"d":2.25003051757813},{"py":63,"a":1,"name":"building-plot","b":0,"tx":426.95,"c":0,"ty":809.3,"px":111,"d":1},{"py":28.5,"a":2.25003051757813,"name":"hole-1","b":0,"tx":81.85,"c":0,"ty":1251.3,"px":35.5,"d":2.25003051757813},{"py":34,"a":1.80490112304688,"name":"hole-2","b":0,"tx":20.8,"c":0,"ty":371.8,"px":51,"d":1.80490112304688},{"py":19,"a":2.25,"name":"bush-7","b":0,"tx":25.45,"c":0,"ty":547.95,"px":41.5,"d":2.25},{"py":15,"a":1.42913818359375,"name":"rock-3","b":0,"tx":99,"c":0,"ty":817.7,"px":27,"d":1.42913818359375},{"a":1,"name":"building-plot","b":0,"tx":119.6,"c":0,"ty":986.4,"d":1},{"py":63,"a":1.03466796875,"name":"building-plot","b":0,"tx":716.35,"c":0,"ty":799.1,"px":111,"d":1},{"a":1,"name":"building-plot","b":0,"tx":212.2,"c":0,"ty":315.15,"d":1},{"a":1,"name":"building-plot","b":0,"tx":701.7,"c":0,"ty":305.7,"d":1},{"py":71.5,"a":1.29998779296875,"name":"tree-0","b":0,"tx":921.5,"c":0,"ty":873.5,"px":61,"d":1.29998779296875},{"py":17.5,"a":0.873611450195313,"name":"rock-0","b":0,"tx":715.6,"c":0,"ty":903.4,"px":39.5,"d":1},{"py":71.5,"a":1.29998779296875,"name":"tree-0","b":0,"tx":99,"c":0,"ty":584.25,"px":61,"d":1.29998779296875},{"py":71.5,"a":1.29998779296875,"name":"tree-0","b":0,"tx":-1.3,"c":0,"ty":752.5,"px":61,"d":1.29998779296875},{"py":15,"a":-1.33915710449219,"name":"rock-3","b":0,"tx":399.1,"c":0,"ty":903.4,"px":27,"d":1.42913818359375},{"a":1,"name":"building-plot","b":0,"tx":716.35,"c":0,"ty":612.1,"d":1},{"a":1,"name":"building-plot","b":0,"tx":134,"c":0,"ty":799.1,"d":1},{"py":66.9,"a":1,"name":"building-plot","b":0,"tx":194.4,"c":0,"ty":1298.75,"px":112.95,"d":1},{"py":76.95,"a":1,"name":"building-plot","b":0,"tx":443.4,"c":0,"ty":1136.4,"px":150.6,"d":1},{"py":66.9,"a":1,"name":"building-plot","b":0,"tx":469.2,"c":0,"ty":458.25,"px":112.95,"d":1},{"py":71.9,"a":1,"name":"building-plot","b":0,"tx":677.8,"c":0,"ty":1298.75,"px":130.55,"d":1}],"hasFinal":false}